Metadata-Version: 2.1
Name: krules-cli
Version: 0.3
Summary: KRules command line utility
Home-page: https://github.com/airspot-dev/krules
Author: Alberto Degli Esposti
Author-email: alberto@arispot.tech
License: Apache Licence 2.0
Keywords: krules knative kubernetes eventing microservices serverless
Platform: UNKNOWN
License-File: LICENSE
